step2.v
module step2(
    input   wire    clk,
    input   wire    rst,
    output  reg     i2c_sda,
    output  wire    i2c_scl
);

//goal to write to device adderss 0x50, 0xaa

localparam STATE_IDLE   = 0;
localparam STATE_START  = 1;
localparam STATE_ADDR   = 2;
localparam STATE_RW     = 3;
localparam STATE_WACK   = 4;
localparam STATE_DATA   = 5;
localparam STATE_STOP   = 6;
localparam STATE_WACK2  = 7;


reg [7:0] state;
reg [6:0] addr;
reg [7:0] count;
reg [7:0] data;
reg i2c_scl_enable = 0;

// hehehe

assign i2c_scl = (i2c_scl_enable == 0) ? 1 : ~clk;

    always @(negedge clk) begin // i2c가 low일 때 data가 들어오도록 하기 위해 negedge로 변경
        if (rst == 1) begin
            i2c_scl_enable <= 0;
        end
        else begin
            if( (state == STATE_IDLE) || (state == STATE_START) || (state == STATE_STOP)) begin
                i2c_scl_enable <= 1;
            end
        end

    end

    always @(posedge clk) begin
        if (rst == 1) begin
            state   <= 0;
            i2c_sda <= 1;
            addr    <= 7'h50;
            count   <= 8'd0;
            data    <= 8'haa;
        end
        else begin
            case (state) 

                STATE_IDLE :  begin // idle
                    i2c_sda <= 1;
                    state   <= STATE_START;
                end

                STATE_START :  begin // start
                    i2c_sda <= 0;
                    state   <= STATE_ADDR;
                    count   <= 6;
                end
        
                STATE_ADDR :  begin // msb address bit
                    i2c_sda <= addr[count];
                    if (count == 0) state <= STATE_RW;
                    else            count <= count -1;
                end

                
                STATE_RW :  begin // bit5
                    i2c_sda <= 1;
                    state   <= STATE_START;
                end

                
                STATE_WACK :  begin // bit4
                    state   <= STATE_START;
                    count   <= 7;
                end

                STATE_DATA : begin 
                    i2c_sda <= data[count];
                    if (count == 0) state <= STATE_WACK;
                    else            count <= count -1;
                end

                STATE_WACK2 : begin // state wack2
                    state <= STATE_STOP;
                end

                STATE_STOP : begin //state stop
                    i2c_sda <= 1;
                    state   <= STATE_IDLE;
                end


            endcase
        end

    end


    /* For Debug FSM State */
    reg [127 : 0] DEBUG_STATE;

    always @(*) begin
        case(state)
            STATE_IDLE  : DEBUG_STATE = "IDLE";
            STATE_START : DEBUG_STATE = "START";
            STATE_ADDR  : DEBUG_STATE = "ADDR";
            STATE_RW    : DEBUG_STATE = "RW";
            STATE_WACK  : DEBUG_STATE = "WACK";
            STATE_DATA  : DEBUG_STATE = "DATA";
            STATE_STOP  : DEBUG_STATE = "STOP";
            STATE_WACK2 : DEBUG_STATE = "WACK2";
        endcase
    end



endmodule

module tb;

    reg     clk;
    reg     rst;
    wire    i2c_sda;
    wire    i2c_scl;

    step2 u0(   .clk(clk), 
                .rst(rst), 
                .i2c_sda(i2c_sda), 
                .i2c_scl(i2c_scl)
    );
    
    // initial begin
    //     i2c_scl = 0;
    //     #5 forever i2c_clk = ~i2c_clk;

    // end

    
    initial begin
        clk = 0;
        forever #5 clk = ~clk;
    end

    
      initial begin
        rst = 1;
        #10
        rst = 0;
        
        // $finish;
    end

    initial begin
        #5000
        $finish;

    end

    initial begin
        $dumpfile("step2.vcd");
        $dumpvars;

    end



endmodule

step2.vcd
$date
	Thu May 11 16:15:19 2023
$end
$version
	Icarus Verilog
$end
$timescale
	1s
$end
$scope module tb $end
$var wire 1 ! i2c_sda $end
$var wire 1 " i2c_scl $end
$var reg 1 # clk $end
$var reg 1 $ rst $end
$scope module u0 $end
$var wire 1 # clk $end
$var wire 1 $ rst $end
$var wire 1 " i2c_scl $end
$var reg 128 % DEBUG_STATE [127:0] $end
$var reg 7 & addr [6:0] $end
$var reg 8 ' count [7:0] $end
$var reg 8 ( data [7:0] $end
$var reg 1 ) i2c_scl_enable $end
$var reg 1 ! i2c_sda $end
$var reg 8 * state [7:0] $end
$upscope $end
$upscope $end
$enddefinitions $end
#0
$dumpvars
bx *
0)
bx (
bx '
bx &
bx %
1$
0#
1"
x!
$end
#5
b1001001010001000100110001000101 %
b10101010 (
b0 '
b1010000 &
1!
b0 *
1#
#10
1)
0#
0$
#15
b101001101010100010000010101001001010100 %
b1 *
0"
1#
#20
1"
0#
#25
b1000001010001000100010001010010 %
b110 '
b10 *
0!
0"
1#
#30
1"
0#
#35
b101 '
1!
0"
1#
#40
1"
0#
#45
b100 '
0!
0"
1#
#50
1"
0#
#55
b11 '
1!
0"
1#
#60
1"
0#
#65
b10 '
0!
0"
1#
#70
1"
0#
#75
b1 '
0"
1#
#80
1"
0#
#85
b0 '
0"
1#
#90
1"
0#
#95
b101001001010111 %
b11 *
0"
1#
#100
1"
0#
#105
b101001101010100010000010101001001010100 %
b1 *
1!
0"
1#
#110
1"
0#
#115
b1000001010001000100010001010010 %
b110 '
b10 *
0!
0"
1#
#120
1"
0#
#125
b101 '
1!
0"
1#
#130
1"
0#
#135
b100 '
0!
0"
1#
#140
1"
0#
#145
b11 '
1!
0"
1#
#150
1"
0#
#155
b10 '
0!
0"
1#
#160
1"
0#
#165
b1 '
0"
1#
#170
1"
0#
#175
b0 '
0"
1#
#180
1"
0#
#185
b101001001010111 %
b11 *
0"
1#
#190
1"
0#
#195
b101001101010100010000010101001001010100 %
b1 *
1!
0"
1#
#200
1"
0#
#205
b1000001010001000100010001010010 %
b110 '
b10 *
0!
0"
1#
#210
1"
0#
#215
b101 '
1!
0"
1#
#220
1"
0#
#225
b100 '
0!
0"
1#
#230
1"
0#
#235
b11 '
1!
0"
1#
#240
1"
0#
#245
b10 '
0!
0"
1#
#250
1"
0#
#255
b1 '
0"
1#
#260
1"
0#
#265
b0 '
0"
1#
#270
1"
0#
#275
b101001001010111 %
b11 *
0"
1#
#280
1"
0#
#285
b101001101010100010000010101001001010100 %
b1 *
1!
0"
1#
#290
1"
0#
#295
b1000001010001000100010001010010 %
b110 '
b10 *
0!
0"
1#
#300
1"
0#
#305
b101 '
1!
0"
1#
#310
1"
0#
#315
b100 '
0!
0"
1#
#320
1"
0#
#325
b11 '
1!
0"
1#
#330
1"
0#
#335
b10 '
0!
0"
1#
#340
1"
0#
#345
b1 '
0"
1#
#350
1"
0#
#355
b0 '
0"
1#
#360
1"
0#
#365
b101001001010111 %
b11 *
0"
1#
#370
1"
0#
#375
b101001101010100010000010101001001010100 %
b1 *
1!
0"
1#
#380
1"
0#
#385
b1000001010001000100010001010010 %
b110 '
b10 *
0!
0"
1#
#390
1"
0#
#395
b101 '
1!
0"
1#
#400
1"
0#
#405
b100 '
0!
0"
1#
#410
1"
0#
#415
b11 '
1!
0"
1#
#420
1"
0#
#425
b10 '
0!
0"
1#
#430
1"
0#
#435
b1 '
0"
1#
#440
1"
0#
#445
b0 '
0"
1#
#450
1"
0#
#455
b101001001010111 %
b11 *
0"
1#
#460
1"
0#
#465
b101001101010100010000010101001001010100 %
b1 *
1!
0"
1#
#470
1"
0#
#475
b1000001010001000100010001010010 %
b110 '
b10 *
0!
0"
1#
#480
1"
0#
#485
b101 '
1!
0"
1#
#490
1"
0#
#495
b100 '
0!
0"
1#
#500
1"
0#
#505
b11 '
1!
0"
1#
#510
1"
0#
#515
b10 '
0!
0"
1#
#520
1"
0#
#525
b1 '
0"
1#
#530
1"
0#
#535
b0 '
0"
1#
#540
1"
0#
#545
b101001001010111 %
b11 *
0"
1#
#550
1"
0#
#555
b101001101010100010000010101001001010100 %
b1 *
1!
0"
1#
#560
1"
0#
#565
b1000001010001000100010001010010 %
b110 '
b10 *
0!
0"
1#
#570
1"
0#
#575
b101 '
1!
0"
1#
#580
1"
0#
#585
b100 '
0!
0"
1#
#590
1"
0#
#595
b11 '
1!
0"
1#
#600
1"
0#
#605
b10 '
0!
0"
1#
#610
1"
0#
#615
b1 '
0"
1#
#620
1"
0#
#625
b0 '
0"
1#
#630
1"
0#
#635
b101001001010111 %
b11 *
0"
1#
#640
1"
0#
#645
b101001101010100010000010101001001010100 %
b1 *
1!
0"
1#
#650
1"
0#
#655
b1000001010001000100010001010010 %
b110 '
b10 *
0!
0"
1#
#660
1"
0#
#665
b101 '
1!
0"
1#
#670
1"
0#
#675
b100 '
0!
0"
1#
#680
1"
0#
#685
b11 '
1!
0"
1#
#690
1"
0#
#695
b10 '
0!
0"
1#
#700
1"
0#
#705
b1 '
0"
1#
#710
1"
0#
#715
b0 '
0"
1#
#720
1"
0#
#725
b101001001010111 %
b11 *
0"
1#
#730
1"
0#
#735
b101001101010100010000010101001001010100 %
b1 *
1!
0"
1#
#740
1"
0#
#745
b1000001010001000100010001010010 %
b110 '
b10 *
0!
0"
1#
#750
1"
0#
#755
b101 '
1!
0"
1#
#760
1"
0#
#765
b100 '
0!
0"
1#
#770
1"
0#
#775
b11 '
1!
0"
1#
#780
1"
0#
#785
b10 '
0!
0"
1#
#790
1"
0#
#795
b1 '
0"
1#
#800
1"
0#
#805
b0 '
0"
1#
#810
1"
0#
#815
b101001001010111 %
b11 *
0"
1#
#820
1"
0#
#825
b101001101010100010000010101001001010100 %
b1 *
1!
0"
1#
#830
1"
0#
#835
b1000001010001000100010001010010 %
b110 '
b10 *
0!
0"
1#
#840
1"
0#
#845
b101 '
1!
0"
1#
#850
1"
0#
#855
b100 '
0!
0"
1#
#860
1"
0#
#865
b11 '
1!
0"
1#
#870
1"
0#
#875
b10 '
0!
0"
1#
#880
1"
0#
#885
b1 '
0"
1#
#890
1"
0#
#895
b0 '
0"
1#
#900
1"
0#
#905
b101001001010111 %
b11 *
0"
1#
#910
1"
0#
#915
b101001101010100010000010101001001010100 %
b1 *
1!
0"
1#
#920
1"
0#
#925
b1000001010001000100010001010010 %
b110 '
b10 *
0!
0"
1#
#930
1"
0#
#935
b101 '
1!
0"
1#
#940
1"
0#
#945
b100 '
0!
0"
1#
#950
1"
0#
#955
b11 '
1!
0"
1#
#960
1"
0#
#965
b10 '
0!
0"
1#
#970
1"
0#
#975
b1 '
0"
1#
#980
1"
0#
#985
b0 '
0"
1#
#990
1"
0#
#995
b101001001010111 %
b11 *
0"
1#
#1000
1"
0#
#1005
b101001101010100010000010101001001010100 %
b1 *
1!
0"
1#
#1010
1"
0#
#1015
b1000001010001000100010001010010 %
b110 '
b10 *
0!
0"
1#
#1020
1"
0#
#1025
b101 '
1!
0"
1#
#1030
1"
0#
#1035
b100 '
0!
0"
1#
#1040
1"
0#
#1045
b11 '
1!
0"
1#
#1050
1"
0#
#1055
b10 '
0!
0"
1#
#1060
1"
0#
#1065
b1 '
0"
1#
#1070
1"
0#
#1075
b0 '
0"
1#
#1080
1"
0#
#1085
b101001001010111 %
b11 *
0"
1#
#1090
1"
0#
#1095
b101001101010100010000010101001001010100 %
b1 *
1!
0"
1#
#1100
1"
0#
#1105
b1000001010001000100010001010010 %
b110 '
b10 *
0!
0"
1#
#1110
1"
0#
#1115
b101 '
1!
0"
1#
#1120
1"
0#
#1125
b100 '
0!
0"
1#
#1130
1"
0#
#1135
b11 '
1!
0"
1#
#1140
1"
0#
#1145
b10 '
0!
0"
1#
#1150
1"
0#
#1155
b1 '
0"
1#
#1160
1"
0#
#1165
b0 '
0"
1#
#1170
1"
0#
#1175
b101001001010111 %
b11 *
0"
1#
#1180
1"
0#
#1185
b101001101010100010000010101001001010100 %
b1 *
1!
0"
1#
#1190
1"
0#
#1195
b1000001010001000100010001010010 %
b110 '
b10 *
0!
0"
1#
#1200
1"
0#
#1205
b101 '
1!
0"
1#
#1210
1"
0#
#1215
b100 '
0!
0"
1#
#1220
1"
0#
#1225
b11 '
1!
0"
1#
#1230
1"
0#
#1235
b10 '
0!
0"
1#
#1240
1"
0#
#1245
b1 '
0"
1#
#1250
1"
0#
#1255
b0 '
0"
1#
#1260
1"
0#
#1265
b101001001010111 %
b11 *
0"
1#
#1270
1"
0#
#1275
b101001101010100010000010101001001010100 %
b1 *
1!
0"
1#
#1280
1"
0#
#1285
b1000001010001000100010001010010 %
b110 '
b10 *
0!
0"
1#
#1290
1"
0#
#1295
b101 '
1!
0"
1#
#1300
1"
0#
#1305
b100 '
0!
0"
1#
#1310
1"
0#
#1315
b11 '
1!
0"
1#
#1320
1"
0#
#1325
b10 '
0!
0"
1#
#1330
1"
0#
#1335
b1 '
0"
1#
#1340
1"
0#
#1345
b0 '
0"
1#
#1350
1"
0#
#1355
b101001001010111 %
b11 *
0"
1#
#1360
1"
0#
#1365
b101001101010100010000010101001001010100 %
b1 *
1!
0"
1#
#1370
1"
0#
#1375
b1000001010001000100010001010010 %
b110 '
b10 *
0!
0"
1#
#1380
1"
0#
#1385
b101 '
1!
0"
1#
#1390
1"
0#
#1395
b100 '
0!
0"
1#
#1400
1"
0#
#1405
b11 '
1!
0"
1#
#1410
1"
0#
#1415
b10 '
0!
0"
1#
#1420
1"
0#
#1425
b1 '
0"
1#
#1430
1"
0#
#1435
b0 '
0"
1#
#1440
1"
0#
#1445
b101001001010111 %
b11 *
0"
1#
#1450
1"
0#
#1455
b101001101010100010000010101001001010100 %
b1 *
1!
0"
1#
#1460
1"
0#
#1465
b1000001010001000100010001010010 %
b110 '
b10 *
0!
0"
1#
#1470
1"
0#
#1475
b101 '
1!
0"
1#
#1480
1"
0#
#1485
b100 '
0!
0"
1#
#1490
1"
0#
#1495
b11 '
1!
0"
1#
#1500
1"
0#
#1505
b10 '
0!
0"
1#
#1510
1"
0#
#1515
b1 '
0"
1#
#1520
1"
0#
#1525
b0 '
0"
1#
#1530
1"
0#
#1535
b101001001010111 %
b11 *
0"
1#
#1540
1"
0#
#1545
b101001101010100010000010101001001010100 %
b1 *
1!
0"
1#
#1550
1"
0#
#1555
b1000001010001000100010001010010 %
b110 '
b10 *
0!
0"
1#
#1560
1"
0#
#1565
b101 '
1!
0"
1#
#1570
1"
0#
#1575
b100 '
0!
0"
1#
#1580
1"
0#
#1585
b11 '
1!
0"
1#
#1590
1"
0#
#1595
b10 '
0!
0"
1#
#1600
1"
0#
#1605
b1 '
0"
1#
#1610
1"
0#
#1615
b0 '
0"
1#
#1620
1"
0#
#1625
b101001001010111 %
b11 *
0"
1#
#1630
1"
0#
#1635
b101001101010100010000010101001001010100 %
b1 *
1!
0"
1#
#1640
1"
0#
#1645
b1000001010001000100010001010010 %
b110 '
b10 *
0!
0"
1#
#1650
1"
0#
#1655
b101 '
1!
0"
1#
#1660
1"
0#
#1665
b100 '
0!
0"
1#
#1670
1"
0#
#1675
b11 '
1!
0"
1#
#1680
1"
0#
#1685
b10 '
0!
0"
1#
#1690
1"
0#
#1695
b1 '
0"
1#
#1700
1"
0#
#1705
b0 '
0"
1#
#1710
1"
0#
#1715
b101001001010111 %
b11 *
0"
1#
#1720
1"
0#
#1725
b101001101010100010000010101001001010100 %
b1 *
1!
0"
1#
#1730
1"
0#
#1735
b1000001010001000100010001010010 %
b110 '
b10 *
0!
0"
1#
#1740
1"
0#
#1745
b101 '
1!
0"
1#
#1750
1"
0#
#1755
b100 '
0!
0"
1#
#1760
1"
0#
#1765
b11 '
1!
0"
1#
#1770
1"
0#
#1775
b10 '
0!
0"
1#
#1780
1"
0#
#1785
b1 '
0"
1#
#1790
1"
0#
#1795
b0 '
0"
1#
#1800
1"
0#
#1805
b101001001010111 %
b11 *
0"
1#
#1810
1"
0#
#1815
b101001101010100010000010101001001010100 %
b1 *
1!
0"
1#
#1820
1"
0#
#1825
b1000001010001000100010001010010 %
b110 '
b10 *
0!
0"
1#
#1830
1"
0#
#1835
b101 '
1!
0"
1#
#1840
1"
0#
#1845
b100 '
0!
0"
1#
#1850
1"
0#
#1855
b11 '
1!
0"
1#
#1860
1"
0#
#1865
b10 '
0!
0"
1#
#1870
1"
0#
#1875
b1 '
0"
1#
#1880
1"
0#
#1885
b0 '
0"
1#
#1890
1"
0#
#1895
b101001001010111 %
b11 *
0"
1#
#1900
1"
0#
#1905
b101001101010100010000010101001001010100 %
b1 *
1!
0"
1#
#1910
1"
0#
#1915
b1000001010001000100010001010010 %
b110 '
b10 *
0!
0"
1#
#1920
1"
0#
#1925
b101 '
1!
0"
1#
#1930
1"
0#
#1935
b100 '
0!
0"
1#
#1940
1"
0#
#1945
b11 '
1!
0"
1#
#1950
1"
0#
#1955
b10 '
0!
0"
1#
#1960
1"
0#
#1965
b1 '
0"
1#
#1970
1"
0#
#1975
b0 '
0"
1#
#1980
1"
0#
#1985
b101001001010111 %
b11 *
0"
1#
#1990
1"
0#
#1995
b101001101010100010000010101001001010100 %
b1 *
1!
0"
1#
#2000
1"
0#
#2005
b1000001010001000100010001010010 %
b110 '
b10 *
0!
0"
1#
#2010
1"
0#
#2015
b101 '
1!
0"
1#
#2020
1"
0#
#2025
b100 '
0!
0"
1#
#2030
1"
0#
#2035
b11 '
1!
0"
1#
#2040
1"
0#
#2045
b10 '
0!
0"
1#
#2050
1"
0#
#2055
b1 '
0"
1#
#2060
1"
0#
#2065
b0 '
0"
1#
#2070
1"
0#
#2075
b101001001010111 %
b11 *
0"
1#
#2080
1"
0#
#2085
b101001101010100010000010101001001010100 %
b1 *
1!
0"
1#
#2090
1"
0#
#2095
b1000001010001000100010001010010 %
b110 '
b10 *
0!
0"
1#
#2100
1"
0#
#2105
b101 '
1!
0"
1#
#2110
1"
0#
#2115
b100 '
0!
0"
1#
#2120
1"
0#
#2125
b11 '
1!
0"
1#
#2130
1"
0#
#2135
b10 '
0!
0"
1#
#2140
1"
0#
#2145
b1 '
0"
1#
#2150
1"
0#
#2155
b0 '
0"
1#
#2160
1"
0#
#2165
b101001001010111 %
b11 *
0"
1#
#2170
1"
0#
#2175
b101001101010100010000010101001001010100 %
b1 *
1!
0"
1#
#2180
1"
0#
#2185
b1000001010001000100010001010010 %
b110 '
b10 *
0!
0"
1#
#2190
1"
0#
#2195
b101 '
1!
0"
1#
#2200
1"
0#
#2205
b100 '
0!
0"
1#
#2210
1"
0#
#2215
b11 '
1!
0"
1#
#2220
1"
0#
#2225
b10 '
0!
0"
1#
#2230
1"
0#
#2235
b1 '
0"
1#
#2240
1"
0#
#2245
b0 '
0"
1#
#2250
1"
0#
#2255
b101001001010111 %
b11 *
0"
1#
#2260
1"
0#
#2265
b101001101010100010000010101001001010100 %
b1 *
1!
0"
1#
#2270
1"
0#
#2275
b1000001010001000100010001010010 %
b110 '
b10 *
0!
0"
1#
#2280
1"
0#
#2285
b101 '
1!
0"
1#
#2290
1"
0#
#2295
b100 '
0!
0"
1#
#2300
1"
0#
#2305
b11 '
1!
0"
1#
#2310
1"
0#
#2315
b10 '
0!
0"
1#
#2320
1"
0#
#2325
b1 '
0"
1#
#2330
1"
0#
#2335
b0 '
0"
1#
#2340
1"
0#
#2345
b101001001010111 %
b11 *
0"
1#
#2350
1"
0#
#2355
b101001101010100010000010101001001010100 %
b1 *
1!
0"
1#
#2360
1"
0#
#2365
b1000001010001000100010001010010 %
b110 '
b10 *
0!
0"
1#
#2370
1"
0#
#2375
b101 '
1!
0"
1#
#2380
1"
0#
#2385
b100 '
0!
0"
1#
#2390
1"
0#
#2395
b11 '
1!
0"
1#
#2400
1"
0#
#2405
b10 '
0!
0"
1#
#2410
1"
0#
#2415
b1 '
0"
1#
#2420
1"
0#
#2425
b0 '
0"
1#
#2430
1"
0#
#2435
b101001001010111 %
b11 *
0"
1#
#2440
1"
0#
#2445
b101001101010100010000010101001001010100 %
b1 *
1!
0"
1#
#2450
1"
0#
#2455
b1000001010001000100010001010010 %
b110 '
b10 *
0!
0"
1#
#2460
1"
0#
#2465
b101 '
1!
0"
1#
#2470
1"
0#
#2475
b100 '
0!
0"
1#
#2480
1"
0#
#2485
b11 '
1!
0"
1#
#2490
1"
0#
#2495
b10 '
0!
0"
1#
#2500
1"
0#
#2505
b1 '
0"
1#
#2510
1"
0#
#2515
b0 '
0"
1#
#2520
1"
0#
#2525
b101001001010111 %
b11 *
0"
1#
#2530
1"
0#
#2535
b101001101010100010000010101001001010100 %
b1 *
1!
0"
1#
#2540
1"
0#
#2545
b1000001010001000100010001010010 %
b110 '
b10 *
0!
0"
1#
#2550
1"
0#
#2555
b101 '
1!
0"
1#
#2560
1"
0#
#2565
b100 '
0!
0"
1#
#2570
1"
0#
#2575
b11 '
1!
0"
1#
#2580
1"
0#
#2585
b10 '
0!
0"
1#
#2590
1"
0#
#2595
b1 '
0"
1#
#2600
1"
0#
#2605
b0 '
0"
1#
#2610
1"
0#
#2615
b101001001010111 %
b11 *
0"
1#
#2620
1"
0#
#2625
b101001101010100010000010101001001010100 %
b1 *
1!
0"
1#
#2630
1"
0#
#2635
b1000001010001000100010001010010 %
b110 '
b10 *
0!
0"
1#
#2640
1"
0#
#2645
b101 '
1!
0"
1#
#2650
1"
0#
#2655
b100 '
0!
0"
1#
#2660
1"
0#
#2665
b11 '
1!
0"
1#
#2670
1"
0#
#2675
b10 '
0!
0"
1#
#2680
1"
0#
#2685
b1 '
0"
1#
#2690
1"
0#
#2695
b0 '
0"
1#
#2700
1"
0#
#2705
b101001001010111 %
b11 *
0"
1#
#2710
1"
0#
#2715
b101001101010100010000010101001001010100 %
b1 *
1!
0"
1#
#2720
1"
0#
#2725
b1000001010001000100010001010010 %
b110 '
b10 *
0!
0"
1#
#2730
1"
0#
#2735
b101 '
1!
0"
1#
#2740
1"
0#
#2745
b100 '
0!
0"
1#
#2750
1"
0#
#2755
b11 '
1!
0"
1#
#2760
1"
0#
#2765
b10 '
0!
0"
1#
#2770
1"
0#
#2775
b1 '
0"
1#
#2780
1"
0#
#2785
b0 '
0"
1#
#2790
1"
0#
#2795
b101001001010111 %
b11 *
0"
1#
#2800
1"
0#
#2805
b101001101010100010000010101001001010100 %
b1 *
1!
0"
1#
#2810
1"
0#
#2815
b1000001010001000100010001010010 %
b110 '
b10 *
0!
0"
1#
#2820
1"
0#
#2825
b101 '
1!
0"
1#
#2830
1"
0#
#2835
b100 '
0!
0"
1#
#2840
1"
0#
#2845
b11 '
1!
0"
1#
#2850
1"
0#
#2855
b10 '
0!
0"
1#
#2860
1"
0#
#2865
b1 '
0"
1#
#2870
1"
0#
#2875
b0 '
0"
1#
#2880
1"
0#
#2885
b101001001010111 %
b11 *
0"
1#
#2890
1"
0#
#2895
b101001101010100010000010101001001010100 %
b1 *
1!
0"
1#
#2900
1"
0#
#2905
b1000001010001000100010001010010 %
b110 '
b10 *
0!
0"
1#
#2910
1"
0#
#2915
b101 '
1!
0"
1#
#2920
1"
0#
#2925
b100 '
0!
0"
1#
#2930
1"
0#
#2935
b11 '
1!
0"
1#
#2940
1"
0#
#2945
b10 '
0!
0"
1#
#2950
1"
0#
#2955
b1 '
0"
1#
#2960
1"
0#
#2965
b0 '
0"
1#
#2970
1"
0#
#2975
b101001001010111 %
b11 *
0"
1#
#2980
1"
0#
#2985
b101001101010100010000010101001001010100 %
b1 *
1!
0"
1#
#2990
1"
0#
#2995
b1000001010001000100010001010010 %
b110 '
b10 *
0!
0"
1#
#3000
1"
0#
#3005
b101 '
1!
0"
1#
#3010
1"
0#
#3015
b100 '
0!
0"
1#
#3020
1"
0#
#3025
b11 '
1!
0"
1#
#3030
1"
0#
#3035
b10 '
0!
0"
1#
#3040
1"
0#
#3045
b1 '
0"
1#
#3050
1"
0#
#3055
b0 '
0"
1#
#3060
1"
0#
#3065
b101001001010111 %
b11 *
0"
1#
#3070
1"
0#
#3075
b101001101010100010000010101001001010100 %
b1 *
1!
0"
1#
#3080
1"
0#
#3085
b1000001010001000100010001010010 %
b110 '
b10 *
0!
0"
1#
#3090
1"
0#
#3095
b101 '
1!
0"
1#
#3100
1"
0#
#3105
b100 '
0!
0"
1#
#3110
1"
0#
#3115
b11 '
1!
0"
1#
#3120
1"
0#
#3125
b10 '
0!
0"
1#
#3130
1"
0#
#3135
b1 '
0"
1#
#3140
1"
0#
#3145
b0 '
0"
1#
#3150
1"
0#
#3155
b101001001010111 %
b11 *
0"
1#
#3160
1"
0#
#3165
b101001101010100010000010101001001010100 %
b1 *
1!
0"
1#
#3170
1"
0#
#3175
b1000001010001000100010001010010 %
b110 '
b10 *
0!
0"
1#
#3180
1"
0#
#3185
b101 '
1!
0"
1#
#3190
1"
0#
#3195
b100 '
0!
0"
1#
#3200
1"
0#
#3205
b11 '
1!
0"
1#
#3210
1"
0#
#3215
b10 '
0!
0"
1#
#3220
1"
0#
#3225
b1 '
0"
1#
#3230
1"
0#
#3235
b0 '
0"
1#
#3240
1"
0#
#3245
b101001001010111 %
b11 *
0"
1#
#3250
1"
0#
#3255
b101001101010100010000010101001001010100 %
b1 *
1!
0"
1#
#3260
1"
0#
#3265
b1000001010001000100010001010010 %
b110 '
b10 *
0!
0"
1#
#3270
1"
0#
#3275
b101 '
1!
0"
1#
#3280
1"
0#
#3285
b100 '
0!
0"
1#
#3290
1"
0#
#3295
b11 '
1!
0"
1#
#3300
1"
0#
#3305
b10 '
0!
0"
1#
#3310
1"
0#
#3315
b1 '
0"
1#
#3320
1"
0#
#3325
b0 '
0"
1#
#3330
1"
0#
#3335
b101001001010111 %
b11 *
0"
1#
#3340
1"
0#
#3345
b101001101010100010000010101001001010100 %
b1 *
1!
0"
1#
#3350
1"
0#
#3355
b1000001010001000100010001010010 %
b110 '
b10 *
0!
0"
1#
#3360
1"
0#
#3365
b101 '
1!
0"
1#
#3370
1"
0#
#3375
b100 '
0!
0"
1#
#3380
1"
0#
#3385
b11 '
1!
0"
1#
#3390
1"
0#
#3395
b10 '
0!
0"
1#
#3400
1"
0#
#3405
b1 '
0"
1#
#3410
1"
0#
#3415
b0 '
0"
1#
#3420
1"
0#
#3425
b101001001010111 %
b11 *
0"
1#
#3430
1"
0#
#3435
b101001101010100010000010101001001010100 %
b1 *
1!
0"
1#
#3440
1"
0#
#3445
b1000001010001000100010001010010 %
b110 '
b10 *
0!
0"
1#
#3450
1"
0#
#3455
b101 '
1!
0"
1#
#3460
1"
0#
#3465
b100 '
0!
0"
1#
#3470
1"
0#
#3475
b11 '
1!
0"
1#
#3480
1"
0#
#3485
b10 '
0!
0"
1#
#3490
1"
0#
#3495
b1 '
0"
1#
#3500
1"
0#
#3505
b0 '
0"
1#
#3510
1"
0#
#3515
b101001001010111 %
b11 *
0"
1#
#3520
1"
0#
#3525
b101001101010100010000010101001001010100 %
b1 *
1!
0"
1#
#3530
1"
0#
#3535
b1000001010001000100010001010010 %
b110 '
b10 *
0!
0"
1#
#3540
1"
0#
#3545
b101 '
1!
0"
1#
#3550
1"
0#
#3555
b100 '
0!
0"
1#
#3560
1"
0#
#3565
b11 '
1!
0"
1#
#3570
1"
0#
#3575
b10 '
0!
0"
1#
#3580
1"
0#
#3585
b1 '
0"
1#
#3590
1"
0#
#3595
b0 '
0"
1#
#3600
1"
0#
#3605
b101001001010111 %
b11 *
0"
1#
#3610
1"
0#
#3615
b101001101010100010000010101001001010100 %
b1 *
1!
0"
1#
#3620
1"
0#
#3625
b1000001010001000100010001010010 %
b110 '
b10 *
0!
0"
1#
#3630
1"
0#
#3635
b101 '
1!
0"
1#
#3640
1"
0#
#3645
b100 '
0!
0"
1#
#3650
1"
0#
#3655
b11 '
1!
0"
1#
#3660
1"
0#
#3665
b10 '
0!
0"
1#
#3670
1"
0#
#3675
b1 '
0"
1#
#3680
1"
0#
#3685
b0 '
0"
1#
#3690
1"
0#
#3695
b101001001010111 %
b11 *
0"
1#
#3700
1"
0#
#3705
b101001101010100010000010101001001010100 %
b1 *
1!
0"
1#
#3710
1"
0#
#3715
b1000001010001000100010001010010 %
b110 '
b10 *
0!
0"
1#
#3720
1"
0#
#3725
b101 '
1!
0"
1#
#3730
1"
0#
#3735
b100 '
0!
0"
1#
#3740
1"
0#
#3745
b11 '
1!
0"
1#
#3750
1"
0#
#3755
b10 '
0!
0"
1#
#3760
1"
0#
#3765
b1 '
0"
1#
#3770
1"
0#
#3775
b0 '
0"
1#
#3780
1"
0#
#3785
b101001001010111 %
b11 *
0"
1#
#3790
1"
0#
#3795
b101001101010100010000010101001001010100 %
b1 *
1!
0"
1#
#3800
1"
0#
#3805
b1000001010001000100010001010010 %
b110 '
b10 *
0!
0"
1#
#3810
1"
0#
#3815
b101 '
1!
0"
1#
#3820
1"
0#
#3825
b100 '
0!
0"
1#
#3830
1"
0#
#3835
b11 '
1!
0"
1#
#3840
1"
0#
#3845
b10 '
0!
0"
1#
#3850
1"
0#
#3855
b1 '
0"
1#
#3860
1"
0#
#3865
b0 '
0"
1#
#3870
1"
0#
#3875
b101001001010111 %
b11 *
0"
1#
#3880
1"
0#
#3885
b101001101010100010000010101001001010100 %
b1 *
1!
0"
1#
#3890
1"
0#
#3895
b1000001010001000100010001010010 %
b110 '
b10 *
0!
0"
1#
#3900
1"
0#
#3905
b101 '
1!
0"
1#
#3910
1"
0#
#3915
b100 '
0!
0"
1#
#3920
1"
0#
#3925
b11 '
1!
0"
1#
#3930
1"
0#
#3935
b10 '
0!
0"
1#
#3940
1"
0#
#3945
b1 '
0"
1#
#3950
1"
0#
#3955
b0 '
0"
1#
#3960
1"
0#
#3965
b101001001010111 %
b11 *
0"
1#
#3970
1"
0#
#3975
b101001101010100010000010101001001010100 %
b1 *
1!
0"
1#
#3980
1"
0#
#3985
b1000001010001000100010001010010 %
b110 '
b10 *
0!
0"
1#
#3990
1"
0#
#3995
b101 '
1!
0"
1#
#4000
1"
0#
#4005
b100 '
0!
0"
1#
#4010
1"
0#
#4015
b11 '
1!
0"
1#
#4020
1"
0#
#4025
b10 '
0!
0"
1#
#4030
1"
0#
#4035
b1 '
0"
1#
#4040
1"
0#
#4045
b0 '
0"
1#
#4050
1"
0#
#4055
b101001001010111 %
b11 *
0"
1#
#4060
1"
0#
#4065
b101001101010100010000010101001001010100 %
b1 *
1!
0"
1#
#4070
1"
0#
#4075
b1000001010001000100010001010010 %
b110 '
b10 *
0!
0"
1#
#4080
1"
0#
#4085
b101 '
1!
0"
1#
#4090
1"
0#
#4095
b100 '
0!
0"
1#
#4100
1"
0#
#4105
b11 '
1!
0"
1#
#4110
1"
0#
#4115
b10 '
0!
0"
1#
